pysqly/__init__.py
pysqly/cli.py
pysqly/connectors/__init__.py
pysqly/connectors/base.py
pysqly/connectors/database.py
pysqly/connectors/factory.py
pysqly/connectors/interface.py
pysqly/connectors/mariadb.py
pysqly/connectors/mssql.py
pysqly/connectors/oracle.py
pysqly/connectors/postgres.py
pysqly/connectors/sqlite.py
pysqly/core/__init__.py
pysqly/core/executor.py
pysqly/core/parser.py
pysqly/core/utils.py
pysqly/errors/__init__.py
pysqly/errors/base.py
pysqly/errors/connector.py
pysqly/errors/execution.py
pysqly/errors/parse.py
pysqly-0.57.0.dist-info/LICENSE
pysqly-0.57.0.dist-info/METADATA
pysqly-0.57.0.dist-info/WHEEL
pysqly-0.57.0.dist-info/entry_points.txt
pysqly-0.57.0.dist-info/top_level.txt
pysqly-0.57.0.dist-info/RECORD
