Metadata-Version: 2.2
Name: pysqly
Version: 0.57.0
Summary: SQL with YAML - A simplified query language for multiple databases
Home-page: https://github.com/Standard-Query-Language/pySQLY
Author: Standard Query Language
Author-email: Standard Query Language <example@example.com>
License: MIT
Project-URL: Homepage, https://github.com/Standard-Query-Language/pySQLY
Project-URL: Bug Tracker, https://github.com/Standard-Query-Language/pySQLY/issues
Classifier: Development Status :: 4 - Beta
Classifier: Intended Audience :: Developers
Classifier: License :: OSI Approved :: MIT License
Classifier: Programming Language :: Python :: 3
Classifier: Programming Language :: Python :: 3.9
Classifier: Programming Language :: Python :: 3.10
Classifier: Programming Language :: Python :: 3.11
Classifier: Topic :: Database
Classifier: Topic :: Software Development :: Libraries :: Python Modules
Requires-Python: >=3.9
License-File: LICENSE
Requires-Dist: pyyaml>=6.0
Provides-Extra: mariadb
Requires-Dist: mysql-connector-python>=8.0; extra == "mariadb"
Provides-Extra: postgres
Requires-Dist: psycopg2>=2.9; extra == "postgres"
Provides-Extra: oracle
Requires-Dist: cx_Oracle>=8.0; extra == "oracle"
Provides-Extra: mssql
Requires-Dist: pyodbc>=4.0; extra == "mssql"
Provides-Extra: all
Requires-Dist: mysql-connector-python>=8.0; extra == "all"
Requires-Dist: psycopg2>=2.9; extra == "all"
Requires-Dist: cx_Oracle>=8.0; extra == "all"
Requires-Dist: pyodbc>=4.0; extra == "all"
Provides-Extra: dev
Requires-Dist: pytest>=7.0; extra == "dev"
Requires-Dist: black>=23.0; extra == "dev"
Requires-Dist: isort>=5.0; extra == "dev"
Requires-Dist: ruff>=0.0.1; extra == "dev"
Requires-Dist: pre-commit>=3.0; extra == "dev"
Dynamic: author
Dynamic: home-page
Dynamic: requires-python
